galaxy/__init__.py
galaxy/py.typed
galaxy/tool_util/__init__.py
galaxy/tool_util/edam_util.py
galaxy/tool_util/fetcher.py
galaxy/tool_util/lint.py
galaxy/tool_util/loader.py
galaxy/tool_util/loader_directory.py
galaxy/tool_util/model_factory.py
galaxy/tool_util/output_checker.py
galaxy/tool_util/provided_metadata.py
galaxy/tool_util/validate_test_format.py
galaxy/tool_util/version.py
galaxy/tool_util/biotools/__init__.py
galaxy/tool_util/biotools/interface.py
galaxy/tool_util/biotools/source.py
galaxy/tool_util/client/__init__.py
galaxy/tool_util/client/landing.py
galaxy/tool_util/client/staging.py
galaxy/tool_util/cwl/__init__.py
galaxy/tool_util/cwl/cwltool_deps.py
galaxy/tool_util/cwl/parser.py
galaxy/tool_util/cwl/representation.py
galaxy/tool_util/cwl/runnable.py
galaxy/tool_util/cwl/runtime_actions.py
galaxy/tool_util/cwl/schema.py
galaxy/tool_util/cwl/util.py
galaxy/tool_util/data/__init__.py
galaxy/tool_util/data/_schema.py
galaxy/tool_util/data/bundles/__init__.py
galaxy/tool_util/data/bundles/models.py
galaxy/tool_util/deps/__init__.py
galaxy/tool_util/deps/brew_exts.py
galaxy/tool_util/deps/brew_util.py
galaxy/tool_util/deps/commands.py
galaxy/tool_util/deps/conda_compat.py
galaxy/tool_util/deps/conda_util.py
galaxy/tool_util/deps/container_classes.py
galaxy/tool_util/deps/container_volumes.py
galaxy/tool_util/deps/containers.py
galaxy/tool_util/deps/dependencies.py
galaxy/tool_util/deps/docker_util.py
galaxy/tool_util/deps/dockerfiles.py
galaxy/tool_util/deps/installable.py
galaxy/tool_util/deps/requirements.py
galaxy/tool_util/deps/singularity_util.py
galaxy/tool_util/deps/views.py
galaxy/tool_util/deps/container_resolvers/__init__.py
galaxy/tool_util/deps/container_resolvers/explicit.py
galaxy/tool_util/deps/container_resolvers/mulled.py
galaxy/tool_util/deps/container_resolvers/test.py
galaxy/tool_util/deps/mulled/__init__.py
galaxy/tool_util/deps/mulled/_cli.py
galaxy/tool_util/deps/mulled/get_tests.py
galaxy/tool_util/deps/mulled/invfile.lua
galaxy_tool_util-25.0.3.dist-info/licenses/LICENSE
galaxy_tool_util-25.0.3.dist-info/METADATA
galaxy_tool_util-25.0.3.dist-info/WHEEL
galaxy_tool_util-25.0.3.dist-info/entry_points.txt
galaxy_tool_util-25.0.3.dist-info/top_level.txt
galaxy_tool_util-25.0.3.dist-info/RECORD
