Metadata-Version: 2.4
Name: galaxy-tool-util
Version: 25.0.3
Summary: Galaxy tool and tool dependency utilities
Home-page: https://github.com/galaxyproject/galaxy
Author: Galaxy Project and Community
Author-email: galaxy-committers@lists.galaxyproject.org
License: AFL
Keywords: Galaxy
Classifier: Development Status :: 5 - Production/Stable
Classifier: Environment :: Console
Classifier: Intended Audience :: Developers
Classifier: License :: OSI Approved :: Academic Free License (AFL)
Classifier: Natural Language :: English
Classifier: Operating System :: POSIX
Classifier: Programming Language :: Python :: 3
Classifier: Programming Language :: Python :: 3.8
Classifier: Programming Language :: Python :: 3.9
Classifier: Programming Language :: Python :: 3.10
Classifier: Programming Language :: Python :: 3.11
Classifier: Programming Language :: Python :: 3.12
Classifier: Programming Language :: Python :: 3.13
Classifier: Topic :: Software Development
Classifier: Topic :: Software Development :: Code Generators
Classifier: Topic :: Software Development :: Testing
Requires-Python: >=3.8
License-File: LICENSE
Requires-Dist: galaxy-tool-util-models
Requires-Dist: galaxy-util[image-util]>=22.1
Requires-Dist: conda-package-streaming
Requires-Dist: lxml!=4.2.2
Requires-Dist: MarkupSafe
Requires-Dist: packaging
Requires-Dist: pydantic!=2.6.0,!=2.6.1,>=2
Requires-Dist: PyYAML
Requires-Dist: requests
Requires-Dist: sortedcontainers
Requires-Dist: typing-extensions
Provides-Extra: cwl
Requires-Dist: cwltool>=3.1.20230624081518; extra == "cwl"
Provides-Extra: mulled
Requires-Dist: jinja2; extra == "mulled"
Requires-Dist: Whoosh; extra == "mulled"
Provides-Extra: edam
Requires-Dist: edam-ontology; extra == "edam"
Provides-Extra: extended-assertions
Requires-Dist: numpy; extra == "extended-assertions"
Requires-Dist: pysam; extra == "extended-assertions"
Requires-Dist: pillow; extra == "extended-assertions"
Requires-Dist: tifffile; extra == "extended-assertions"
Dynamic: license-file
